mapping_kit-0.1.0a22.dist-info/METADATA
mapping_kit-0.1.0a22.dist-info/WHEEL
mapping_kit-0.1.0a22.dist-info/entry_points.txt
mapping_kit-0.1.0a22.dist-info/licenses/LICENSE
mapping_kit/__init__.py
mapping_kit/attribute_dict.py
mapping_kit/cartesian_iterator.py
mapping_kit/caseinsensitive_dict.py
mapping_kit/group_dict.py
mapping_kit/group_dict_backup.py
mapping_kit/nested_dict.py
mapping_kit/nested_dict_backup.py
mapping_kit/super_dict.py
mapping_kit/utils.py
mapping_kit/version.py
mapping_kit/virtual_iterable.py
mapping_kit-0.1.0a22.dist-info/RECORD
