Metadata-Version: 2.1
Name: mapping-kit
Version: 0.1.0a22
Summary: Additional useful mappings
Keywords: mapping,dictionary
Author-Email: "Aalap Shah (aka fishfin)" <shah.aalap@gmail.com>
License: MIT License
Classifier: Development Status :: 2 - Pre-Alpha
Classifier: Intended Audience :: Developers
Classifier: License :: OSI Approved :: MIT License
Classifier: Operating System :: OS Independent
Classifier: Programming Language :: Python :: 3
Classifier: Programming Language :: Python :: 3 :: Only
Classifier: Programming Language :: Python :: 3.11
Classifier: Programming Language :: Python :: 3.12
Classifier: Programming Language :: Python :: 3.13
Classifier: Programming Language :: Python :: 3.14
Classifier: Topic :: Software Development
Classifier: Topic :: Utilities
Project-URL: Homepage, https://gitlab.com/shah-aalap/python-mapping-kit
Requires-Python: >=3.11
